[
  {
    "source": "lecityf_public",
    "sourceId": "boao-tarlatamab",
    "name": "注射用塔拉妥单抗",
    "nameEn": "Tarlatamab for Injection",
    "productType": "drug",
    "indication": "经治广泛期小细胞肺癌",
    "diseaseLabel": "小细胞肺癌",
    "diseaseSlugs": ["xiao-xi-bao"],
    "manufacturer": "Amgen",
    "originRegion": "美国",
    "status": "active",
    "summary": "全球首个获批用于小细胞肺癌的 DLL3 靶向双特异性 T 细胞衔接蛋白，国内尚未上市，可在乐城先行区特许使用。",
    "usageNote": "须本人前往海南博鳌乐城指定医疗机构就诊，药品在院内使用，不得携带离院。",
    "officialUrl": "http://www.lczxyf.com/",
    "crawledAt": "2026-05-30"
  },
  {
    "source": "lecityf_public",
    "sourceId": "boao-quizartinib",
    "name": "盐酸奎扎替尼片",
    "nameEn": "Quizartinib Tablets",
    "productType": "drug",
    "indication": "FLT3-ITD 突变急性髓系白血病",
    "diseaseLabel": "AML",
    "diseaseSlugs": ["aml"],
    "manufacturer": "Daiichi Sankyo",
    "originRegion": "日本/美国",
    "status": "active",
    "summary": "FLT3-ITD 突变 AML 靶向治疗药物，已在多国获批，国内尚未上市。",
    "usageNote": "乐城特许使用，需经先行区医疗机构多学科评估后制定方案。",
    "officialUrl": "http://www.lczxyf.com/",
    "crawledAt": "2026-05-30"
  },
  {
    "source": "lecityf_public",
    "sourceId": "boao-seladelpar",
    "name": "Seladelpar",
    "nameEn": "Seladelpar",
    "productType": "drug",
    "indication": "原发性胆汁性胆管炎",
    "diseaseLabel": "自身免疫性肝病",
    "diseaseSlugs": ["other-unspecified"],
    "manufacturer": "CymaBay",
    "originRegion": "美国",
    "status": "active",
    "summary": "原发性胆汁性胆管炎（PBC）在研/新获批疗法，乐城特许引进品种之一。",
    "usageNote": "需在乐城具备相应诊疗能力的医疗机构使用。",
    "officialUrl": "http://www.lczxyf.com/",
    "crawledAt": "2026-05-30"
  },
  {
    "source": "lecityf_public",
    "sourceId": "boao-filsuvez",
    "name": "Filsuvez",
    "nameEn": "Oleogel-S10 (Filsuvez)",
    "productType": "drug",
    "indication": "营养不良型大疱性表皮松解症",
    "diseaseLabel": "罕见皮肤病",
    "diseaseSlugs": ["fabry", "other-unspecified"],
    "manufacturer": "Chiesi",
    "originRegion": "欧盟",
    "status": "active",
    "summary": "用于罕见皮肤病大疱性表皮松解症的外用凝胶，国内未上市，乐城特许可及。",
    "usageNote": "罕见病用药，需经乐城专家委员会及医疗机构评估后使用。",
    "officialUrl": "http://www.lczxyf.com/",
    "crawledAt": "2026-05-30"
  },
  {
    "source": "lecityf_public",
    "sourceId": "boao-lecanemab",
    "name": "仑卡奈单抗",
    "nameEn": "Lecanemab",
    "productType": "drug",
    "indication": "早期阿尔茨海默病",
    "diseaseLabel": "阿尔茨海默病",
    "diseaseSlugs": ["other-unspecified"],
    "manufacturer": "Eisai/Biogen",
    "originRegion": "美国/日本",
    "status": "active",
    "summary": "AD 靶向单抗疗法，已在美日等地获批，国内尚未全面上市，乐城可提供特许使用通道。",
    "usageNote": "需完成认知评估与淀粉样蛋白检测后，在乐城指定 memory clinic 使用。",
    "officialUrl": "http://www.lczxyf.com/",
    "crawledAt": "2026-05-30"
  },
  {
    "source": "hn_medical_catalog",
    "sourceId": "boao-mirdametinib",
    "name": "Mirdametinib",
    "nameEn": "Mirdametinib",
    "productType": "drug",
    "indication": "神经纤维瘤病相关丛状神经纤维瘤",
    "diseaseLabel": "神经纤维瘤病",
    "diseaseSlugs": ["other-unspecified"],
    "manufacturer": "SpringWorks",
    "originRegion": "美国",
    "status": "active",
    "summary": "NF1 相关 pNF 的 MEK 抑制剂，收录于乐城特许药械公开目录。",
    "usageNote": "须在乐城先行区合规医疗机构内使用。",
    "officialUrl": "http://www.hn-medical.com/",
    "crawledAt": "2026-05-30"
  },
  {
    "source": "lecityf_public",
    "sourceId": "boao-varipulse",
    "name": "VARIPULSE 脉冲电场消融系统",
    "nameEn": "VARIPULSE Platform",
    "productType": "device",
    "indication": "心房颤动导管消融",
    "diseaseLabel": "心律失常",
    "diseaseSlugs": ["other-unspecified"],
    "manufacturer": "Johnson & Johnson",
    "originRegion": "美国",
    "status": "active",
    "summary": "脉冲电场（PFA）消融系统，用于房颤治疗，属乐城特许引进创新医疗器械。",
    "usageNote": "器械在乐城指定医院内由有资质团队实施手术。",
    "officialUrl": "http://www.lczxyf.com/",
    "crawledAt": "2026-05-30"
  },
  {
    "source": "lecityf_public",
    "sourceId": "boao-neuroguard",
    "name": "Neuroguard IEP 系统",
    "nameEn": "Neuroguard IEP System",
    "productType": "device",
    "indication": "神经介入治疗",
    "diseaseLabel": "脑血管病",
    "diseaseSlugs": ["other-unspecified"],
    "manufacturer": "Imperative Care",
    "originRegion": "美国",
    "status": "active",
    "summary": "神经介入器械，用于急性缺血性卒中取栓等场景，乐城特许器械目录收录。",
    "usageNote": "需在具备神经介入资质的乐城医疗机构使用。",
    "officialUrl": "http://www.lczxyf.com/",
    "crawledAt": "2026-05-30"
  },
  {
    "source": "hn_medical_catalog",
    "sourceId": "boao-osimertinib-lecheng",
    "name": "奥希替尼（乐城特许补充规格）",
    "nameEn": "Osimertinib (Lecheng special access)",
    "productType": "drug",
    "indication": "EGFR突变非小细胞肺癌",
    "diseaseLabel": "非小细胞肺癌 EGFR",
    "diseaseSlugs": ["fei-ai-egfr"],
    "manufacturer": "AstraZeneca",
    "originRegion": "英国",
    "status": "active",
    "summary": "针对国内暂不可及规格或联合方案的 EGFR-TKI，可通过乐城特许政策合法使用。",
    "usageNote": "须前往乐城指定肿瘤中心，由多学科团队制定方案。",
    "officialUrl": "http://www.hn-medical.com/",
    "crawledAt": "2026-05-30"
  },
  {
    "source": "hn_medical_catalog",
    "sourceId": "boao-zolgensma-lecheng",
    "name": "Onasemnogene Abeparvovec（Zolgensma）",
    "nameEn": "Zolgensma",
    "productType": "drug",
    "indication": "脊髓性肌萎缩症（SMA）",
    "diseaseLabel": "SMA",
    "diseaseSlugs": ["sma"],
    "manufacturer": "Novartis",
    "originRegion": "美国",
    "status": "active",
    "summary": "SMA 基因治疗产品，国内尚未全面可及，乐城为重要特许引进通道之一。",
    "usageNote": "基因治疗需在乐城具备资质的中心完成评估与给药。",
    "officialUrl": "http://www.hn-medical.com/",
    "crawledAt": "2026-05-30"
  }
]
